iencoder/__init__.py
iencoder/iencoder.py
iencoder-0.2.dist-info/METADATA
iencoder-0.2.dist-info/WHEEL
iencoder-0.2.dist-info/top_level.txt
iencoder-0.2.dist-info/RECORD
